thewhitetools/__init__.py
thewhitetools-0.0.1.dist-info/LICENSE
thewhitetools-0.0.1.dist-info/METADATA
thewhitetools-0.0.1.dist-info/WHEEL
thewhitetools-0.0.1.dist-info/top_level.txt
thewhitetools-0.0.1.dist-info/RECORD
